{
  "BO_1_Garisenda.jpg": {
    "place": "Torre della Garisenda",
    "city": "Bologna",
    "description": {
      "it": "Torre della Garisenda",
      "en": "Garisenda Tower",
      "de": "Turm Garisenda"
    },
    "credit": "<a href=\"https://commons.wikimedia.org/wiki/File:BO_-_Torre_Garisenda.jpg\">EvelinaRibarova</a>, <a href=\"https://creativecommons.org/licenses/by-sa/4.0\">CC BY-SA 4.0</a>, via Wikimedia Commons"
  },
  "BO_2_Basilica_S_Domenico.jpg": {
    "place": "Basilica di San Domenico",
    "city": "Bologna",
    "description": {
      "it": "Basilica di San Domenico",
      "en": "Basilica of San Domenico",
      "de": "Basilika San Domenico"
    },
    "credit": "<a href=\"https://commons.wikimedia.org/wiki/File:Basilica_of_St._Domenico_Bologna.jpg\">Elemari-r95</a>, <a href=\"https://creativecommons.org/licenses/by-sa/4.0\">CC BY-SA 4.0</a>, via Wikimedia Commons"
  },
  "CA_1_Castello_Poppi.jpg": {
    "place": "Castello di Poppi",
    "city": "Casentino",
    "description": {
      "it": "Castello di Poppi",
      "en": "Poppi Castle",
      "de": "Burg Poppi"
    },
    "credit": "<a href=\"https://commons.wikimedia.org/wiki/File:Poppi_-_Castello_dei_Conti_Guidi_-_2025-09-01_14-07-37_001.jpg\">Fabioarg</a>, <a href=\"https://creativecommons.org/licenses/by-sa/4.0\">CC BY-SA 4.0</a>, via Wikimedia Commons"
  },
  "CA_2_Castello_Romena.jpg": {
    "place": "Castello di Romena",
    "city": "Casentino",
    "description": {
      "it": "Castello di Romena",
      "en": "Romena Castle",
      "de": "Burg Romena"
    },
    "credit": "<a href=\"https://commons.wikimedia.org/wiki/File:Castello_di_romena,_mastio_04.JPG\">Sailko</a>, <a href=\"https://creativecommons.org/licenses/by-sa/4.0\">CC BY-SA 4.0</a>, via Wikimedia Commons"
  },
  "FO_1_Porta_Schiavonia.jfif": {
    "place": "Porta Schiavonia",
    "city": "Forlì",
    "description": {
      "it": "Porta Schiavonia",
      "en": "Schiavonia Gate",
      "de": "Tor Schiavonia"
    },
    "credit": "<a href=\"https://commons.wikimedia.org/wiki/File:Porta_Schiavonia_(Forl%C3%AC).JPG\">Perkele at Italian Wikipedia</a>, <a href=\"https://creativecommons.org/licenses/by-sa/3.0\">CC BY-SA 3.0</a>, via Wikimedia Commons"
  },
  "FO_2_Palazzo_Paulucci.jpg": {
    "place": "Palazzo Paulucci di Calboli d’Aste",
    "city": "Forlì",
    "description": {
      "it": "Palazzo Paulucci di Calboli d’Aste",
      "en": "Paulucci di Calboli d’Aste Palace",
      "de": "Palast Paulucci di Calboli d’Aste"
    },
    "credit": "<a href=\"https://commons.wikimedia.org/wiki/File:Palazzo_Paolucci_Sede_della_Prefettura_2010_-_panoramio.jpg\">piero drago</a>, <a href=\"https://creativecommons.org/licenses/by-sa/3.0\">CC BY-SA 3.0</a>, via Wikimedia Commons"
  },
  "FO_3_Piazza_Saffi.jpg": {
    "place": "Piazza Saffi",
    "city": "Forlì",
    "description": {
      "it": "Piazza Saffi",
      "en": "Saffi Square",
      "de": "Saffi Platz"
    },
    "credit": "<a href=\"https://commons.wikimedia.org/wiki/File:Forl%C3%AC_Piazza_Aurelio_Saffi_10.jpg\">Zairon</a>, <a href=\"https://creativecommons.org/licenses/by-sa/4.0\">CC BY-SA 4.0</a>, via Wikimedia Commons"
  },
  "LU_1_Mulazzo.jpg": {
    "place": "Museo Dantesco Lunigianese",
    "city": "Lunigiana",
    "description": {
      "it": "Vista di Mulazzo",
      "en": "View of Mulazzo",
      "de": "Blick auf Mulazzo"
    },
    "credit": "<a href=\"https://commons.wikimedia.org/wiki/File:Mulazzo_(Massa-Carrara)_2.jpg\">Salvatore Lombardi</a>, <a href=\"https://creativecommons.org/licenses/by-sa/3.0\">CC BY-SA 3.0</a>, via Wikimedia Commons"
  },
  "LU_2_Stemma_Spino_Secco.png": {
    "place": "Castello di Giovagallo",
    "city": "Lunigiana",
    "description": {
      "it": "Stemma del Casato dei Malaspina dello Spino Secco",
      "en": "Coat of arms of the House of Malaspina (Spino Secco)",
      "de": "Wappen des Hauses Malaspina (Spino Secco)"
    },
    "credit": "<a href=\"https://commons.wikimedia.org/wiki/File:Coat_of_arms_of_the_House_of_Malaspina_(Spino_Secco)_(1).svg\">FootKalos1597</a>, <a href=\"https://creativecommons.org/licenses/by-sa/4.0\">CC BY-SA 4.0</a>, via Wikimedia Commons"
  },
  "RA_1_Museo_Dante.jpg": {
    "place": "Museo Dante",
    "city": "Ravenna",
    "description": {
      "it": "Busto di Dante presso il Museo Dante di Ravenna",
      "en": "Bust of Dante at the Dante Museum in Ravenna",
      "de": "Büste von Dante im Dante-Museum in Ravenna"
    },
    "credit": "<a href=\"https://commons.wikimedia.org/wiki/File:DanteMuseum02.jpg\">Georges Jansoone</a>, <a href=\"http://creativecommons.org/licenses/by-sa/3.0/\">CC BY-SA 3.0</a>, via Wikimedia Commons"
  },
  "RA_2_Tomba_Dante.jpg": {
    "place": "Tomba di Dante",
    "city": "Ravenna",
    "description": {
      "it": "Tomba di Dante",
      "en": "Dante's Tomb",
      "de": "Dantes Grab"
    },
    "credit": "<a href=\"https://commons.wikimedia.org/wiki/File:Ravenna,_tomba_di_Dante_(05).jpg\">Gianni Careddu</a>, <a href=\"https://creativecommons.org/licenses/by-sa/4.0\">CC BY-SA 4.0</a>, via Wikimedia Commons"
  },
  "RA_3_Quadrarco_Braccioforte.jpg": {
    "place": "Quadrarco di Braccioforte",
    "city": "Ravenna",
    "description": {
      "it": "Targa che ricorda il temporaneo ricollocamento delle spoglie di Dante durante la Seconda Guerra Mondiale",
      "en": "Plaque commemorating the temporary relocation of Dante's remains during World War II",
      "de": "Tafel zur Erinnerung an die vorübergehende Verlegung von Dantes Überresten im Zweiten Weltkrieg"
    },
    "credit": "<a href=\"https://commons.wikimedia.org/wiki/File:Ravenna_-_Tomba_di_Dante_-_La_targa_nel_quadrarco_di_Braccioforte.JPG\">Monica Rondoni</a>, <a href=\"https://creativecommons.org/licenses/by-sa/4.0\">CC BY-SA 4.0</a>, via Wikimedia Commons"
  },
  "RA_4_Murales_Dante.jpg": {
    "place": "Murales di Dante di Kobra",
    "city": "Ravenna",
    "description": {
      "it": "Murales di Dante di Kobra",
      "en": "Dante mural by Kobra",
      "de": "Dante-Mural von Kobra"
    },
    "credit": "<a href=\"https://commons.wikimedia.org/wiki/File:Dante_Alighieri_2.jpg\">Renzo favalli</a>, <a href=\"https://creativecommons.org/licenses/by-sa/4.0\">CC BY-SA 4.0</a>, via Wikimedia Commons"
  },
  "TR_1_Ponte_Dante.jpg": {
    "place": "Ponte Dante",
    "city": "Treviso",
    "description": {
      "it": "Ponte Dante",
      "en": "Dante Bridge",
      "de": "Dante-Brücke"
    },
    "credit": "<a href=\"https://commons.wikimedia.org/wiki/File:Treviso_-_Ponte_Dante_-_2023-09-08_15-10-37_001.jpg\">Liridon</a>, <a href=\"https://creativecommons.org/licenses/by-sa/4.0\">CC BY-SA 4.0</a>, via Wikimedia Commons"
  },
  "TR_2_Chiesa_S_Francesco.jpg": {
    "place": "Chiesa di San Francesco",
    "city": "Treviso",
    "description": {
      "it": "Chiesa di San Francesco",
      "en": "Church of San Francesco",
      "de": "Kirche San Francesco"
    },
    "credit": "<a href=\"https://commons.wikimedia.org/wiki/File:Chiesa_Convento_San_Francesco_Facciata_Treviso.jpg\">Didier Descouens</a>, <a href=\"https://creativecommons.org/licenses/by-sa/4.0\">CC BY-SA 4.0</a>, via Wikimedia Commons"
  },
  "VR_1_Piazza_Dante.jpg": {
    "place": "Piazza Dante",
    "city": "Verona",
    "description": {
      "it": "Piazza Dante",
      "en": "Dante Square",
      "de": "Danteplatz"
    },
    "credit": "<a href=\"https://commons.wikimedia.org/wiki/File:Piazza_dei_Signori_(Verona)_-_Casa_della_Piet%C3%A0.jpg\">Didier Descouens</a>, <a href=\"https://creativecommons.org/licenses/by-sa/4.0\">CC BY-SA 4.0</a>, via Wikimedia Commons"
  },
  "VR_2_Chiesa_S_Elena.jpg": {
    "place": "Chiesa di Sant'Elena",
    "city": "Verona",
    "description": {
      "it": "Chiesa di Sant'Elena",
      "en": "Church of Saint Helena",
      "de": "Kirche St. Helena"
    },
    "credit": "<a href=\"https://commons.wikimedia.org/wiki/File:Duomo_(Verona)_-_Sant%27Elena_(Verona)_-_Facade.JPG\">Verona Cathedral</a>, <a href=\"https://creativecommons.org/licenses/by-sa/4.0\">CC BY-SA 4.0</a>, via Wikimedia Commons"
  },
  "VR_3_Casa_Romeo.jpg": {
    "place": "Casa di Romeo",
    "city": "Verona",
    "description": {
      "it": "Casa di Romeo",
      "en": "Romeo's House",
      "de": "Haus von Romeo"
    },
    "credit": "<a href=\"https://commons.wikimedia.org/wiki/File:Casa_di_Cagnolo_Nogarola_(Casa_di_Romeo),_Verona_(37779314011).jpg\">Dimitris Kamaras from Athens, Greece</a>, <a href=\"https://creativecommons.org/licenses/by/2.0\">CC BY 2.0</a>, via Wikimedia Commons"
  },
  "VR_4_Porta_Borsari.jpg": {
    "place": "Porta Borsari",
    "city": "Verona",
    "description": {
      "it": "Porta Borsari",
      "en": "Porta Borsari",
      "de": "Porta Borsari"
    },
    "credit": "<a href=\"https://commons.wikimedia.org/wiki/File:Porta_Borsari_(Verona).jpg\">Didier Descouens</a>, <a href=\"https://creativecommons.org/licenses/by-sa/4.0\">CC BY-SA 4.0</a>, via Wikimedia Commons"
  }
}